dlgis/__about__.py
dlgis/__init__.py
dlgis/dlgis.py
dlgis-0.1.0.data/scripts/dlgis_export
dlgis-0.1.0.data/scripts/dlgis_import
dlgis-0.1.0.dist-info/AUTHORS
dlgis-0.1.0.dist-info/LICENSE
dlgis-0.1.0.dist-info/METADATA
dlgis-0.1.0.dist-info/WHEEL
dlgis-0.1.0.dist-info/top_level.txt
dlgis-0.1.0.dist-info/RECORD
