Metadata-Version: 2.1
Name: dlgis
Version: 0.1.0
Summary: Data Library GIS datasets
Home-page: https://bitbucket.org/iridl/dlgis
Author: IRI, Columbia University
Author-email: help@iri.columbia.edu
License: UNKNOWN
Project-URL: Bug Reports, https://bitbucket.org/iridl/dlgis/issues
Platform: UNKNOWN
Classifier: Programming Language :: Python :: 3
Classifier: License :: OSI Approved :: MIT License
Classifier: Operating System :: OS Independent
Requires-Python: >= 3.7
Requires-Dist: click (==7.1.*)
Requires-Dist: pyshp (==2.1.*)
Requires-Dist: gdal (==3.0.*)
